LICENSE
MANIFEST.in
README.rst
setup.py
django_oscar_testsupport.egg-info/PKG-INFO
django_oscar_testsupport.egg-info/SOURCES.txt
django_oscar_testsupport.egg-info/dependency_links.txt
django_oscar_testsupport.egg-info/requires.txt
django_oscar_testsupport.egg-info/top_level.txt
oscar_testsupport/__init__.py
oscar_testsupport/contextmanagers.py
oscar_testsupport/decorators.py
oscar_testsupport/factories.py
oscar_testsupport/testcases.py