Metadata-Version: 1.0
Name: django-oscar-testsupport
Version: 0.4
Summary: Testing utilities for Oscar
Home-page: https://github.com/tangentlabs/django-oscar-testsupport
Author: David Winterbottom
Author-email: david.winterbottom@tangentlabs.co.uk
License: Copyright (c) 2011, Tangent Communications PLC and individual contributors.
